README.md
pyproject.toml
netbox_smartos/__init__.py
netbox_smartos/custom_fields.py
netbox_smartos/jobs.py
netbox_smartos/models.py
netbox_smartos.egg-info/PKG-INFO
netbox_smartos.egg-info/SOURCES.txt
netbox_smartos.egg-info/dependency_links.txt
netbox_smartos.egg-info/requires.txt
netbox_smartos.egg-info/top_level.txt
netbox_smartos/__pycache__/__init__.cpython-312.pyc
netbox_smartos/__pycache__/custom_fields.cpython-312.pyc
netbox_smartos/__pycache__/jobs.cpython-312.pyc
netbox_smartos/__pycache__/models.cpython-312.pyc
netbox_smartos/api/__init__.py
netbox_smartos/api/serializers.py
netbox_smartos/api/urls.py
netbox_smartos/api/views.py
netbox_smartos/api/__pycache__/__init__.cpython-312.pyc
netbox_smartos/api/__pycache__/serializers.cpython-312.pyc
netbox_smartos/api/__pycache__/urls.cpython-312.pyc
netbox_smartos/api/__pycache__/views.cpython-312.pyc
netbox_smartos/management/commands/__init__.py
netbox_smartos/management/commands/create_netbox_smartos_initial_data.py
netbox_smartos/management/commands/__pycache__/__init__.cpython-312.pyc
netbox_smartos/management/commands/__pycache__/create_netbox_smartos_initial_data.cpython-312.pyc
netbox_smartos/migrations/0001_initial.py
netbox_smartos/migrations/__init__.py
netbox_smartos/migrations/__pycache__/0001_initial.cpython-312.pyc
netbox_smartos/migrations/__pycache__/__init__.cpython-312.pyc