Metadata-Version: 2.4
Name: netbox-smartos
Version: 26.1.10.1
Author-email: SkyLime GmbH <info@skylime.net>
Classifier: Programming Language :: Python :: 3
Requires-Dist: django-annoying>=0.10.8
